marstime/__init__.py
marstime/_version.py
marstime-0.5.6.dist-info/LICENSE.txt
marstime-0.5.6.dist-info/METADATA
marstime-0.5.6.dist-info/WHEEL
marstime-0.5.6.dist-info/top_level.txt
marstime-0.5.6.dist-info/RECORD
