Metadata-Version: 2.1
Name: marstime
Version: 0.5.6
Summary: marstime library, implements the Mars24 algorithm [Allison and McEwan, 2000]
Home-page: http://code.foldmountain.com/marstime
Author: Christopher Lee
Author-email: lee@foldmountain.com
License: LICENSE.txt
Download-URL: https://bitbucket.org/eelsirhc/marstime/downloads
Platform: UNKNOWN
Classifier: License :: OSI Approved :: BSD License
Classifier: Intended Audience :: Science/Research
Classifier: Programming Language :: Python :: 3
Classifier: Topic :: Scientific/Engineering :: Astronomy
